{
	"pages": [{
		"path": "pages/music/music",
		"style": {
			"navigationBarTitleText": "HZHMusic",
			"enablePullDownRefresh": false
		}
	}, {
		"path": "pages/video-list/video-list",
		"style": {
			"navigationBarTitleText": "视频",
			"enablePullDownRefresh": false
		}
	}, {
		"path": "pages/video-detail/video-detail",
		"style": {
			"navigationBarTitleText": "详情",
			"enablePullDownRefresh": false
		}

	}, {
		"path": "pages/search/search",
		"style": {
			"navigationBarTitleText": "",
			"enablePullDownRefresh": false
		}
	}, {
		"path": "pages/playlist-list/playlist-list",
		"style": {
			"navigationBarTitleText": "歌单广场",
			"enablePullDownRefresh": false
		}
	}, {
		"path": "pages/playlist-detail/playlist-detail",
		"style": {
			"navigationBarTitleText": "歌单详情",
			"enablePullDownRefresh": false
		}
	}    ,{
            "path" : "pages/rank-list/rank-list",
            "style" :                                                                                    
            {
                "navigationBarTitleText": "",
                "enablePullDownRefresh": false
            }
            
        },
        {
          "path" : "pages/music-player/music-player",
          "style" : 
          {
            "navigationBarTitleText" : "",
            "enablePullDownRefresh" : false,
            "navigationStyle":"custom",
            "navigationBarTextStyle": "white"
          }
        }
    ],
	"globalStyle": {
		"navigationBarTextStyle": "black",
		"navigationBarTitleText": "uni-app",
		"navigationBarBackgroundColor": "#F8F8F8",
		"backgroundColor": "#fdfdfd",
		"app-plus": {
			"background": "#efeff4"
		}
	},
	"tabBar": {
    "selectedColor": "#07c160",
		"list": [{
			"text": "音乐",
			"pagePath": "pages/music/music",
			"iconPath": "static/tabbar/yinle.png",
			"selectedIconPath": "static/tabbar/yinle-selected.png"
		}, {
			"text": "视频",
			"pagePath": "pages/video-list/video-list",
			"iconPath": "static/tabbar/shipin.png",
			"selectedIconPath": "static/tabbar/shipin-selected.png"
		}]
	}
}